iots/__init__.py
iots/api.py
iots/apis/__init__.py
iots/apis/actions.py
iots/apis/categories.py
iots/apis/communications.py
iots/apis/email.py
iots/apis/events.py
iots/apis/properties.py
iots/apis/properties_history.py
iots/apis/spaces.py
iots/apis/things.py
iots/internal/__init__.py
iots/internal/content_type.py
iots/internal/resource.py
iots/internal/runtime_expr.py
iots/models/__init__.py
iots/models/basemodel.py
iots/models/exceptions.py
iots/models/extensions/__init__.py
iots/models/extensions/pagination.py
iots/models/models.py
iots/models/pagination.py
iots/models/primitives.py
iots/security.py
iots-0.5.0.dist-info/LICENSE.txt
iots-0.5.0.dist-info/METADATA
iots-0.5.0.dist-info/WHEEL
iots-0.5.0.dist-info/RECORD
