Metadata-Version: 2.1
Name: iots
Version: 0.5.0
Summary: A Python client for the Altair IoT Studio API
Home-page: https://github.com/altairengineering/iots-python
Keywords: iot,altair,smartcore,smartworks,api,client,library
Author: Daniel Sánchez Gallego
Author-email: dsanchez@altair.com
Requires-Python: >=3.8,<4.0
Classifier: Programming Language :: Python :: 3
Classifier: Programming Language :: Python :: 3.8
Classifier: Programming Language :: Python :: 3.9
Classifier: Programming Language :: Python :: 3.10
Classifier: Programming Language :: Python :: 3.11
Classifier: Topic :: Software Development :: Libraries
Requires-Dist: pydantic (>=1.10.21,<2.0.0)
Requires-Dist: requests (>=2.31.0,<3.0.0)
Requires-Dist: xmltodict (>=0.14.2,<0.15.0)
Project-URL: Documentation, https://iots.readthedocs.io/
Project-URL: Repository, https://github.com/altairengineering/iots-python
